pytest_django_ifactory/__init__.py
pytest_django_ifactory/defaults.py
pytest_django_ifactory/flags.py
pytest_django_ifactory/ifactory.py
pytest_django_ifactory/plugin.py
pytest_django_ifactory/py.typed
pytest_django_ifactory/typing.py
pytest_django_ifactory-1.3.0.dist-info/licenses/LICENSE
pytest_django_ifactory-1.3.0.dist-info/METADATA
pytest_django_ifactory-1.3.0.dist-info/WHEEL
pytest_django_ifactory-1.3.0.dist-info/entry_points.txt
pytest_django_ifactory-1.3.0.dist-info/top_level.txt
pytest_django_ifactory-1.3.0.dist-info/RECORD
