Metadata-Version: 2.4
Name: pytest-django-ifactory
Version: 1.3.0
Summary: A model instance factory for pytest-django
Author-email: Mattias Jakobsson <mjakob422@gmail.com>
License: BSD-3-Clause
Project-URL: Homepage, https://gitlab.com/gorilladev/pytest-django-ifactory
Keywords: pytest,django,database,testing
Classifier: Development Status :: 5 - Production/Stable
Classifier: Environment :: Plugins
Classifier: Framework :: Django
Classifier: Framework :: Pytest
Classifier: Intended Audience :: Developers
Classifier: License :: OSI Approved :: BSD License
Classifier: Programming Language :: Python :: 3
Classifier: Programming Language :: Python :: 3.9
Classifier: Programming Language :: Python :: 3.10
Classifier: Programming Language :: Python :: 3.11
Classifier: Programming Language :: Python :: 3.12
Classifier: Programming Language :: Python :: 3.13
Classifier: Topic :: Software Development :: Testing
Classifier: Typing :: Typed
Requires-Python: >=3.9
License-File: LICENSE
Requires-Dist: pytest-django
Provides-Extra: dev
Requires-Dist: build; extra == "dev"
Requires-Dist: check-manifest; extra == "dev"
Requires-Dist: django<6,>=4.2; extra == "dev"
Requires-Dist: django-stubs; extra == "dev"
Requires-Dist: mypy; extra == "dev"
Requires-Dist: pillow; extra == "dev"
Requires-Dist: pre-commit; extra == "dev"
Requires-Dist: psycopg2-binary; extra == "dev"
Requires-Dist: pytest-cov; extra == "dev"
Requires-Dist: ruff; extra == "dev"
Requires-Dist: typing_extensions>=4; extra == "dev"
Requires-Dist: twine; extra == "dev"
Requires-Dist: wheel; extra == "dev"
Dynamic: license-file
